[[0, 0, 0], {"dropout1_rate": 0.7746713016708047, "dropout2_rate": 0.6818768555440728, "lr": 6.574198059281823e-05, "num_dense_layers": 1, "optimizer": "SGD", "start_neurons_units": 111, "sgd_momentum": 0.2753102288028251}, {"model_based_pick": false}]
[[0, 0, 1], {"dropout1_rate": 0.33037713767982485, "dropout2_rate": 0.25967278026887003, "lr": 0.00043874606427708886, "num_dense_layers": 3, "optimizer": "SGD", "start_neurons_units": 69, "dense1_units": 17, "dense2_units": 19, "sgd_momentum": 0.44699702384780876}, {"model_based_pick": false}]
[[0, 0, 2], {"dropout1_rate": 0.6712135216011014, "dropout2_rate": 0.12528159962727434, "lr": 0.06817042289538981, "num_dense_layers": 3, "optimizer": "Adam", "start_neurons_units": 196, "dense1_units": 77, "dense2_units": 32}, {"model_based_pick": false}]
[[0, 0, 3], {"dropout1_rate": 0.6225489256138814, "dropout2_rate": 0.3809096212794711, "lr": 0.00020060865300579263, "num_dense_layers": 2, "optimizer": "SGD", "start_neurons_units": 36, "dense1_units": 24, "sgd_momentum": 0.36336315478409736}, {"model_based_pick": false}]
[[0, 0, 4], {"dropout1_rate": 0.5032191903827219, "dropout2_rate": 0.4609212868909689, "lr": 0.01973571827167781, "num_dense_layers": 3, "optimizer": "Adam", "start_neurons_units": 161, "dense1_units": 14, "dense2_units": 7}, {"model_based_pick": false}]
[[0, 0, 5], {"dropout1_rate": 0.4655437099990193, "dropout2_rate": 0.5195622018134445, "lr": 5.3486881899132696e-05, "num_dense_layers": 2, "optimizer": "SGD", "start_neurons_units": 44, "dense1_units": 124, "sgd_momentum": 0.8475437238933935}, {"model_based_pick": false}]
[[0, 0, 6], {"dropout1_rate": 0.7010703427235827, "dropout2_rate": 0.22861974743911673, "lr": 0.00016298324306299135, "num_dense_layers": 2, "optimizer": "SGD", "start_neurons_units": 65, "dense1_units": 100, "sgd_momentum": 0.34309917864983674}, {"model_based_pick": false}]
[[0, 0, 7], {"dropout1_rate": 0.4905568866318994, "dropout2_rate": 0.8685759298242067, "lr": 1.4633737639600455e-05, "num_dense_layers": 2, "optimizer": "SGD", "start_neurons_units": 36, "dense1_units": 90, "sgd_momentum": 0.8259829538196602}, {"model_based_pick": false}]
[[0, 0, 8], {"dropout1_rate": 0.39573818918605796, "dropout2_rate": 0.5979109704783447, "lr": 0.032567690265122524, "num_dense_layers": 3, "optimizer": "Adam", "start_neurons_units": 87, "dense1_units": 18, "dense2_units": 6}, {"model_based_pick": false}]
[[0, 0, 9], {"dropout1_rate": 0.7228069332478919, "dropout2_rate": 0.4005214917428941, "lr": 8.53009271435655e-06, "num_dense_layers": 2, "optimizer": "Adam", "start_neurons_units": 187, "dense1_units": 30}, {"model_based_pick": false}]
[[0, 0, 10], {"dropout1_rate": 0.29316642287727934, "dropout2_rate": 0.629459496587755, "lr": 6.207010488100043e-05, "num_dense_layers": 2, "optimizer": "Adam", "start_neurons_units": 361, "dense1_units": 92}, {"model_based_pick": false}]
[[0, 0, 11], {"dropout1_rate": 0.6882384991274075, "dropout2_rate": 0.2904492586148991, "lr": 1.719263586124624e-05, "num_dense_layers": 2, "optimizer": "Adam", "start_neurons_units": 284, "dense1_units": 64}, {"model_based_pick": false}]
[[0, 0, 12], {"dropout1_rate": 0.043511800730783055, "dropout2_rate": 0.028721318397194617, "lr": 0.0008882196507789965, "num_dense_layers": 3, "optimizer": "Adam", "start_neurons_units": 63, "dense1_units": 47, "dense2_units": 16}, {"model_based_pick": false}]
[[0, 0, 13], {"dropout1_rate": 0.15398464859890257, "dropout2_rate": 0.32613814809316477, "lr": 1.656579166863501e-05, "num_dense_layers": 3, "optimizer": "Adam", "start_neurons_units": 69, "dense1_units": 47, "dense2_units": 8}, {"model_based_pick": false}]
[[0, 0, 14], {"dropout1_rate": 0.5443911523449694, "dropout2_rate": 0.33795648631067243, "lr": 4.100803863747245e-06, "num_dense_layers": 3, "optimizer": "Adam", "start_neurons_units": 50, "dense1_units": 14, "dense2_units": 8}, {"model_based_pick": false}]
[[0, 0, 15], {"dropout1_rate": 0.6495608228261558, "dropout2_rate": 0.295282054707828, "lr": 0.07956586689696898, "num_dense_layers": 1, "optimizer": "SGD", "start_neurons_units": 70, "sgd_momentum": 0.7223452091788001}, {"model_based_pick": false}]
[[0, 0, 16], {"dropout1_rate": 0.017270373247006032, "dropout2_rate": 0.7954080249371431, "lr": 0.002043758879910851, "num_dense_layers": 2, "optimizer": "SGD", "start_neurons_units": 356, "dense1_units": 12, "sgd_momentum": 0.4091763731247616}, {"model_based_pick": false}]
[[0, 0, 17], {"dropout1_rate": 0.30464827038985265, "dropout2_rate": 0.39973456471682467, "lr": 0.028469737607114423, "num_dense_layers": 2, "optimizer": "Adam", "start_neurons_units": 86, "dense1_units": 47}, {"model_based_pick": false}]
[[0, 0, 18], {"dropout1_rate": 0.11531008519424119, "dropout2_rate": 0.1171000037047089, "lr": 0.0018496495065710348, "num_dense_layers": 3, "optimizer": "Adam", "start_neurons_units": 312, "dense1_units": 39, "dense2_units": 7}, {"model_based_pick": false}]
[[0, 0, 19], {"dropout1_rate": 0.5422935452237279, "dropout2_rate": 0.5445608109788929, "lr": 6.057529043171945e-05, "num_dense_layers": 1, "optimizer": "SGD", "start_neurons_units": 293, "sgd_momentum": 0.5524669634244516}, {"model_based_pick": false}]
[[0, 0, 20], {"dropout1_rate": 0.6728846359195249, "dropout2_rate": 0.5080873118660961, "lr": 0.005788597385613672, "num_dense_layers": 2, "optimizer": "SGD", "start_neurons_units": 165, "dense1_units": 13, "sgd_momentum": 0.15954410245061082}, {"model_based_pick": false}]
[[0, 0, 21], {"dropout1_rate": 0.2816043880842444, "dropout2_rate": 0.3306761988101226, "lr": 5.5045860352843355e-06, "num_dense_layers": 2, "optimizer": "SGD", "start_neurons_units": 58, "dense1_units": 34, "sgd_momentum": 0.7592763188717605}, {"model_based_pick": false}]
[[0, 0, 22], {"dropout1_rate": 0.5307315231429913, "dropout2_rate": 0.013312208859600994, "lr": 0.00544908001656902, "num_dense_layers": 1, "optimizer": "Adam", "start_neurons_units": 125}, {"model_based_pick": false}]
[[0, 0, 23], {"dropout1_rate": 0.5715686740461686, "dropout2_rate": 0.2523612470675467, "lr": 0.04891408180374992, "num_dense_layers": 1, "optimizer": "Adam", "start_neurons_units": 117}, {"model_based_pick": false}]
[[0, 0, 24], {"dropout1_rate": 0.06738874042689812, "dropout2_rate": 0.04687791746059444, "lr": 0.000192589680847709, "num_dense_layers": 3, "optimizer": "Adam", "start_neurons_units": 283, "dense1_units": 27, "dense2_units": 4}, {"model_based_pick": false}]
[[0, 0, 25], {"dropout1_rate": 0.042104879834956345, "dropout2_rate": 0.401737336448485, "lr": 0.00019526210598362008, "num_dense_layers": 2, "optimizer": "Adam", "start_neurons_units": 51, "dense1_units": 53}, {"model_based_pick": false}]
[[0, 0, 26], {"dropout1_rate": 0.549434588894455, "dropout2_rate": 0.869339805560029, "lr": 0.009302232502200745, "num_dense_layers": 1, "optimizer": "SGD", "start_neurons_units": 487, "sgd_momentum": 0.6395883397280449}, {"model_based_pick": false}]
