[[0, 0, 0], {"dropout1_rate": 0.3197529694812728, "dropout2_rate": 0.2276474247174101, "lr": 0.018514526252431787, "num_dense_layers": 3, "optimizer": "SGD", "start_neurons_units": 32, "dense1_units": 51, "dense2_units": 9, "sgd_momentum": 0.34473032485256255}, {"model_based_pick": false}]
[[0, 0, 1], {"dropout1_rate": 0.8179980409240492, "dropout2_rate": 0.06833376187598213, "lr": 9.448444855498323e-06, "num_dense_layers": 3, "optimizer": "Adam", "start_neurons_units": 151, "dense1_units": 46, "dense2_units": 46}, {"model_based_pick": false}]
[[0, 0, 2], {"dropout1_rate": 0.042178391989255194, "dropout2_rate": 0.8454531945895819, "lr": 0.04605247744110167, "num_dense_layers": 2, "optimizer": "SGD", "start_neurons_units": 399, "dense1_units": 11, "sgd_momentum": 0.04552460931240111}, {"model_based_pick": false}]
[[0, 0, 3], {"dropout1_rate": 0.14635125183207073, "dropout2_rate": 0.5384455548246146, "lr": 3.2499698474871704e-06, "num_dense_layers": 1, "optimizer": "SGD", "start_neurons_units": 49, "sgd_momentum": 0.20675919161456963}, {"model_based_pick": false}]
[[0, 0, 4], {"dropout1_rate": 0.4063403538777812, "dropout2_rate": 0.8128851609327256, "lr": 1.3598272280607483e-06, "num_dense_layers": 1, "optimizer": "SGD", "start_neurons_units": 98, "sgd_momentum": 0.15373640545813957}, {"model_based_pick": false}]
[[0, 0, 5], {"dropout1_rate": 0.6916179206091144, "dropout2_rate": 0.30866505021807616, "lr": 2.522219022173909e-06, "num_dense_layers": 1, "optimizer": "Adam", "start_neurons_units": 51}, {"model_based_pick": false}]
[[0, 0, 6], {"dropout1_rate": 0.20499761095375385, "dropout2_rate": 0.22559192441152032, "lr": 0.0008731364211635829, "num_dense_layers": 2, "optimizer": "Adam", "start_neurons_units": 149, "dense1_units": 35}, {"model_based_pick": false}]
[[0, 0, 7], {"dropout1_rate": 0.5181121276614387, "dropout2_rate": 0.7238519241209664, "lr": 0.0004080275536750593, "num_dense_layers": 2, "optimizer": "Adam", "start_neurons_units": 63, "dense1_units": 127}, {"model_based_pick": false}]
[[0, 0, 8], {"dropout1_rate": 0.6156294245946596, "dropout2_rate": 0.7961764836344826, "lr": 8.055667670791727e-05, "num_dense_layers": 3, "optimizer": "Adam", "start_neurons_units": 406, "dense1_units": 30, "dense2_units": 12}, {"model_based_pick": false}]
[[0, 0, 9], {"dropout1_rate": 0.08905218903747095, "dropout2_rate": 0.7916397492892171, "lr": 0.01416490711519476, "num_dense_layers": 1, "optimizer": "Adam", "start_neurons_units": 400}, {"model_based_pick": false}]
[[0, 0, 10], {"dropout1_rate": 0.8175480533507883, "dropout2_rate": 0.6000996410353635, "lr": 1.0326036296211971e-05, "num_dense_layers": 1, "optimizer": "SGD", "start_neurons_units": 213, "sgd_momentum": 0.8230968523998468}, {"model_based_pick": false}]
[[0, 0, 11], {"dropout1_rate": 0.019234092302344276, "dropout2_rate": 0.4177733305887716, "lr": 7.121156377057545e-05, "num_dense_layers": 2, "optimizer": "Adam", "start_neurons_units": 99, "dense1_units": 31}, {"model_based_pick": false}]
[[0, 0, 12], {"dropout1_rate": 0.3983006229385076, "dropout2_rate": 0.7853019804348542, "lr": 0.029509443251727396, "num_dense_layers": 2, "optimizer": "Adam", "start_neurons_units": 388, "dense1_units": 19}, {"model_based_pick": false}]
[[0, 0, 13], {"dropout1_rate": 0.509019080695064, "dropout2_rate": 0.369587291327669, "lr": 0.001195046883115725, "num_dense_layers": 3, "optimizer": "SGD", "start_neurons_units": 33, "dense1_units": 46, "dense2_units": 16, "sgd_momentum": 0.7253171193175793}, {"model_based_pick": false}]
[[0, 0, 14], {"dropout1_rate": 0.6298905527266998, "dropout2_rate": 0.8622246076558999, "lr": 3.2803723994274796e-06, "num_dense_layers": 2, "optimizer": "SGD", "start_neurons_units": 33, "dense1_units": 24, "sgd_momentum": 0.22324356237513404}, {"model_based_pick": false}]
[[0, 0, 15], {"dropout1_rate": 0.5618695674540405, "dropout2_rate": 0.36078185317747774, "lr": 0.00015832385446592516, "num_dense_layers": 2, "optimizer": "Adam", "start_neurons_units": 47, "dense1_units": 69}, {"model_based_pick": false}]
[[0, 0, 16], {"dropout1_rate": 0.04683870663454217, "dropout2_rate": 0.7078323939884128, "lr": 0.0017035198580204903, "num_dense_layers": 1, "optimizer": "Adam", "start_neurons_units": 212}, {"model_based_pick": false}]
[[0, 0, 17], {"dropout1_rate": 0.8216372331385727, "dropout2_rate": 0.7894542564570542, "lr": 0.0015215349147806418, "num_dense_layers": 2, "optimizer": "SGD", "start_neurons_units": 43, "dense1_units": 109, "sgd_momentum": 0.15134112576362957}, {"model_based_pick": false}]
[[0, 0, 18], {"dropout1_rate": 0.23153990698937288, "dropout2_rate": 0.5417559712292155, "lr": 3.349946787980324e-05, "num_dense_layers": 3, "optimizer": "Adam", "start_neurons_units": 303, "dense1_units": 35, "dense2_units": 46}, {"model_based_pick": false}]
[[0, 0, 19], {"dropout1_rate": 0.13508233850240647, "dropout2_rate": 0.6324577776524747, "lr": 6.055816060105027e-05, "num_dense_layers": 2, "optimizer": "SGD", "start_neurons_units": 421, "dense1_units": 32, "sgd_momentum": 0.3845710650538384}, {"model_based_pick": false}]
[[0, 0, 20], {"dropout1_rate": 0.1531019217072737, "dropout2_rate": 0.329712839941872, "lr": 3.70829152741222e-05, "num_dense_layers": 1, "optimizer": "Adam", "start_neurons_units": 40}, {"model_based_pick": false}]
[[0, 0, 21], {"dropout1_rate": 0.7159643313466791, "dropout2_rate": 0.3591077556289156, "lr": 0.0006190995428426271, "num_dense_layers": 3, "optimizer": "Adam", "start_neurons_units": 379, "dense1_units": 79, "dense2_units": 19}, {"model_based_pick": false}]
[[0, 0, 22], {"dropout1_rate": 0.2872022319440637, "dropout2_rate": 0.6623682073184899, "lr": 7.910133135680307e-06, "num_dense_layers": 2, "optimizer": "SGD", "start_neurons_units": 74, "dense1_units": 24, "sgd_momentum": 0.7938264860842414}, {"model_based_pick": false}]
[[0, 0, 23], {"dropout1_rate": 0.3175156057643323, "dropout2_rate": 0.3769846172503271, "lr": 1.0546381971444077e-06, "num_dense_layers": 3, "optimizer": "SGD", "start_neurons_units": 445, "dense1_units": 29, "dense2_units": 33, "sgd_momentum": 0.4042061276487567}, {"model_based_pick": false}]
[[0, 0, 24], {"dropout1_rate": 0.01454180566410297, "dropout2_rate": 0.367279097340872, "lr": 3.0769783161112053e-06, "num_dense_layers": 1, "optimizer": "SGD", "start_neurons_units": 185, "sgd_momentum": 0.49957129754053203}, {"model_based_pick": false}]
[[0, 0, 25], {"dropout1_rate": 0.7535060683658226, "dropout2_rate": 0.16884978587297655, "lr": 0.03129929322480939, "num_dense_layers": 3, "optimizer": "SGD", "start_neurons_units": 78, "dense1_units": 65, "dense2_units": 23, "sgd_momentum": 0.16512253729263338}, {"model_based_pick": false}]
[[0, 0, 26], {"dropout1_rate": 0.17120362618373725, "dropout2_rate": 0.8049315845438513, "lr": 0.00013340280173677744, "num_dense_layers": 3, "optimizer": "SGD", "start_neurons_units": 77, "dense1_units": 41, "dense2_units": 5, "sgd_momentum": 0.2648294273220159}, {"model_based_pick": false}]
