[[0, 0, 0], {"dropout1_rate": 0.8703929332531011, "dropout2_rate": 0.2529087264407907, "lr": 0.00015163272974190543, "num_dense_layers": 3, "optimizer": "Adam", "start_neurons_units": 149, "dense1_units": 48, "dense2_units": 9}, {"model_based_pick": false}]
[[0, 0, 1], {"dropout1_rate": 0.5382618523869146, "dropout2_rate": 0.36561928348927214, "lr": 0.00029291782041911824, "num_dense_layers": 3, "optimizer": "SGD", "start_neurons_units": 48, "dense1_units": 14, "dense2_units": 4, "sgd_momentum": 0.8019088926053238}, {"model_based_pick": false}]
[[0, 0, 2], {"dropout1_rate": 0.2734336845483101, "dropout2_rate": 0.04525056311096614, "lr": 5.098959499233091e-06, "num_dense_layers": 3, "optimizer": "Adam", "start_neurons_units": 301, "dense1_units": 13, "dense2_units": 4}, {"model_based_pick": false}]
[[0, 0, 3], {"dropout1_rate": 0.33143355554552073, "dropout2_rate": 0.8212384908627779, "lr": 5.0063067746955755e-05, "num_dense_layers": 2, "optimizer": "Adam", "start_neurons_units": 265, "dense1_units": 13}, {"model_based_pick": false}]
[[0, 0, 4], {"dropout1_rate": 0.4981450479190971, "dropout2_rate": 0.7084191788199891, "lr": 7.773515579790209e-06, "num_dense_layers": 1, "optimizer": "SGD", "start_neurons_units": 35, "sgd_momentum": 0.7600475732346792}, {"model_based_pick": false}]
[[0, 0, 5], {"dropout1_rate": 0.40789125968144835, "dropout2_rate": 0.2609133632864429, "lr": 0.017185990710803744, "num_dense_layers": 1, "optimizer": "SGD", "start_neurons_units": 32, "sgd_momentum": 0.23560018705142716}, {"model_based_pick": false}]
[[0, 0, 6], {"dropout1_rate": 0.40102258336088137, "dropout2_rate": 0.18823169616679475, "lr": 0.003141368338345185, "num_dense_layers": 3, "optimizer": "Adam", "start_neurons_units": 152, "dense1_units": 65, "dense2_units": 4}, {"model_based_pick": false}]
[[0, 0, 7], {"dropout1_rate": 0.10997981085535934, "dropout2_rate": 0.8256133437175943, "lr": 0.05779967196815441, "num_dense_layers": 2, "optimizer": "Adam", "start_neurons_units": 162, "dense1_units": 40}, {"model_based_pick": false}]
[[0, 0, 8], {"dropout1_rate": 0.19303816522224523, "dropout2_rate": 0.0998882365611388, "lr": 1.4403811716619051e-05, "num_dense_layers": 2, "optimizer": "Adam", "start_neurons_units": 388, "dense1_units": 26}, {"model_based_pick": false}]
[[0, 0, 9], {"dropout1_rate": 0.3737919726271957, "dropout2_rate": 0.23505426576296165, "lr": 8.068367578046882e-05, "num_dense_layers": 3, "optimizer": "SGD", "start_neurons_units": 331, "dense1_units": 9, "dense2_units": 14, "sgd_momentum": 0.6083752564900831}, {"model_based_pick": false}]
[[0, 0, 10], {"dropout1_rate": 0.10831529864189368, "dropout2_rate": 0.8402633703356067, "lr": 0.018514551578167216, "num_dense_layers": 1, "optimizer": "SGD", "start_neurons_units": 54, "sgd_momentum": 0.3582752608482251}, {"model_based_pick": false}]
[[0, 0, 11], {"dropout1_rate": 0.5842569384608737, "dropout2_rate": 0.017137531093292503, "lr": 2.5150201894802134e-05, "num_dense_layers": 1, "optimizer": "SGD", "start_neurons_units": 366, "sgd_momentum": 0.7194902531857742}, {"model_based_pick": false}]
[[0, 0, 12], {"dropout1_rate": 0.4624099107588864, "dropout2_rate": 0.26522250740393577, "lr": 1.819932565349572e-05, "num_dense_layers": 2, "optimizer": "Adam", "start_neurons_units": 52, "dense1_units": 10}, {"model_based_pick": false}]
[[0, 0, 13], {"dropout1_rate": 0.5397685390852244, "dropout2_rate": 0.6965075200393913, "lr": 0.00037187209528617406, "num_dense_layers": 1, "optimizer": "Adam", "start_neurons_units": 287}, {"model_based_pick": false}]
[[0, 0, 14], {"dropout1_rate": 0.07838099964541824, "dropout2_rate": 0.08526779543080347, "lr": 0.0003496399623801679, "num_dense_layers": 1, "optimizer": "SGD", "start_neurons_units": 167, "sgd_momentum": 0.11767149584822707}, {"model_based_pick": false}]
[[0, 0, 15], {"dropout1_rate": 0.46324478892568804, "dropout2_rate": 0.2621615472016766, "lr": 0.029457304462430535, "num_dense_layers": 1, "optimizer": "Adam", "start_neurons_units": 410}, {"model_based_pick": false}]
[[0, 0, 16], {"dropout1_rate": 0.12892845753452797, "dropout2_rate": 0.21866446291794103, "lr": 3.952275279698933e-06, "num_dense_layers": 1, "optimizer": "SGD", "start_neurons_units": 197, "sgd_momentum": 0.16304361309357304}, {"model_based_pick": false}]
[[0, 0, 17], {"dropout1_rate": 0.6911122117515008, "dropout2_rate": 0.3219921969877777, "lr": 0.007439650671079888, "num_dense_layers": 3, "optimizer": "SGD", "start_neurons_units": 135, "dense1_units": 53, "dense2_units": 17, "sgd_momentum": 0.26691354208723334}, {"model_based_pick": false}]
[[0, 0, 18], {"dropout1_rate": 0.5826269565049869, "dropout2_rate": 0.4631659628598534, "lr": 0.027281992823409915, "num_dense_layers": 1, "optimizer": "SGD", "start_neurons_units": 43, "sgd_momentum": 0.9555540774638761}, {"model_based_pick": false}]
[[0, 0, 19], {"dropout1_rate": 0.4561441007389021, "dropout2_rate": 0.6540701001497311, "lr": 0.03846134902763184, "num_dense_layers": 3, "optimizer": "Adam", "start_neurons_units": 102, "dense1_units": 37, "dense2_units": 5}, {"model_based_pick": false}]
[[0, 0, 20], {"dropout1_rate": 0.8745333490855348, "dropout2_rate": 0.4353395356658365, "lr": 0.010037657027101129, "num_dense_layers": 3, "optimizer": "Adam", "start_neurons_units": 273, "dense1_units": 128, "dense2_units": 4}, {"model_based_pick": false}]
[[0, 0, 21], {"dropout1_rate": 0.48087551370682274, "dropout2_rate": 0.8744256460127567, "lr": 2.1012134979969586e-05, "num_dense_layers": 1, "optimizer": "SGD", "start_neurons_units": 46, "sgd_momentum": 0.11397723216875973}, {"model_based_pick": false}]
[[0, 0, 22], {"dropout1_rate": 0.707475741240701, "dropout2_rate": 0.4253023385702682, "lr": 2.4781393368471113e-05, "num_dense_layers": 1, "optimizer": "SGD", "start_neurons_units": 245, "sgd_momentum": 0.44700759521731154}, {"model_based_pick": false}]
[[0, 0, 23], {"dropout1_rate": 0.7514884144908613, "dropout2_rate": 0.571051012244681, "lr": 1.5554324090863894e-05, "num_dense_layers": 3, "optimizer": "SGD", "start_neurons_units": 47, "dense1_units": 26, "dense2_units": 8, "sgd_momentum": 0.31359531132060015}, {"model_based_pick": false}]
[[0, 0, 24], {"dropout1_rate": 0.27988331359559127, "dropout2_rate": 0.517580736202713, "lr": 0.00012373430439618512, "num_dense_layers": 3, "optimizer": "Adam", "start_neurons_units": 57, "dense1_units": 118, "dense2_units": 10}, {"model_based_pick": false}]
[[0, 0, 25], {"dropout1_rate": 0.03598358258044631, "dropout2_rate": 0.17277904149708279, "lr": 0.0008381430657181269, "num_dense_layers": 1, "optimizer": "SGD", "start_neurons_units": 85, "sgd_momentum": 0.9104246090142362}, {"model_based_pick": false}]
[[0, 0, 26], {"dropout1_rate": 0.183840000774373, "dropout2_rate": 0.37132577511722786, "lr": 0.010694907869054799, "num_dense_layers": 3, "optimizer": "Adam", "start_neurons_units": 83, "dense1_units": 105, "dense2_units": 19}, {"model_based_pick": false}]
