[[0, 0, 0], {"dropout1_rate": 0.23854937745518695, "dropout2_rate": 0.866996659972114, "lr": 0.002957090895126487, "num_dense_layers": 2, "optimizer": "SGD", "start_neurons_units": 350, "dense1_units": 14, "sgd_momentum": 0.7413058300576054}, {"model_based_pick": false}]
[[0, 0, 1], {"dropout1_rate": 0.8610368523663692, "dropout2_rate": 0.4246759058364637, "lr": 3.0768467729491654e-05, "num_dense_layers": 2, "optimizer": "SGD", "start_neurons_units": 156, "dense1_units": 28, "sgd_momentum": 0.9153144077799666}, {"model_based_pick": false}]
[[0, 0, 2], {"dropout1_rate": 0.19770137497748458, "dropout2_rate": 0.5149279824879963, "lr": 0.0009052930831580772, "num_dense_layers": 1, "optimizer": "Adam", "start_neurons_units": 62}, {"model_based_pick": false}]
[[0, 0, 3], {"dropout1_rate": 0.007548264854357734, "dropout2_rate": 0.14873860847881942, "lr": 0.018470218085620955, "num_dense_layers": 2, "optimizer": "SGD", "start_neurons_units": 313, "dense1_units": 51, "sgd_momentum": 0.34741732117018564}, {"model_based_pick": false}]
[[0, 0, 4], {"dropout1_rate": 0.8745980624876072, "dropout2_rate": 0.35447970099856285, "lr": 0.042523563862874605, "num_dense_layers": 1, "optimizer": "SGD", "start_neurons_units": 48, "sgd_momentum": 0.9766205460422598}, {"model_based_pick": false}]
[[0, 0, 5], {"dropout1_rate": 0.8023936433599566, "dropout2_rate": 0.38817173101036506, "lr": 0.0010969800401016156, "num_dense_layers": 2, "optimizer": "Adam", "start_neurons_units": 450, "dense1_units": 69}, {"model_based_pick": false}]
[[0, 0, 6], {"dropout1_rate": 0.3260774249134918, "dropout2_rate": 0.11873388094513641, "lr": 1.408777394556689e-05, "num_dense_layers": 2, "optimizer": "SGD", "start_neurons_units": 209, "dense1_units": 10, "sgd_momentum": 0.030586959937711676}, {"model_based_pick": false}]
[[0, 0, 7], {"dropout1_rate": 0.18822768597648362, "dropout2_rate": 0.6162062157612404, "lr": 2.546293710782194e-06, "num_dense_layers": 3, "optimizer": "Adam", "start_neurons_units": 72, "dense1_units": 121, "dense2_units": 42}, {"model_based_pick": false}]
[[0, 0, 8], {"dropout1_rate": 0.16549688467533666, "dropout2_rate": 0.3701802390069455, "lr": 2.55318413213036e-05, "num_dense_layers": 3, "optimizer": "SGD", "start_neurons_units": 164, "dense1_units": 10, "dense2_units": 10, "sgd_momentum": 0.8553774485790456}, {"model_based_pick": false}]
[[0, 0, 9], {"dropout1_rate": 0.3956184637234038, "dropout2_rate": 0.63242346252009, "lr": 0.001407819393613156, "num_dense_layers": 2, "optimizer": "Adam", "start_neurons_units": 288, "dense1_units": 29}, {"model_based_pick": false}]
[[0, 0, 10], {"dropout1_rate": 0.36364892038576707, "dropout2_rate": 0.6849870691311871, "lr": 2.9153105255292692e-05, "num_dense_layers": 2, "optimizer": "SGD", "start_neurons_units": 76, "dense1_units": 8, "sgd_momentum": 0.900230155583372}, {"model_based_pick": false}]
[[0, 0, 11], {"dropout1_rate": 0.2553527659646435, "dropout2_rate": 0.6748950519122936, "lr": 5.162101871587554e-05, "num_dense_layers": 3, "optimizer": "Adam", "start_neurons_units": 243, "dense1_units": 53, "dense2_units": 36}, {"model_based_pick": false}]
[[0, 0, 12], {"dropout1_rate": 0.5825177879265723, "dropout2_rate": 0.3922493405380729, "lr": 0.0053364624830896405, "num_dense_layers": 1, "optimizer": "SGD", "start_neurons_units": 113, "sgd_momentum": 0.983309602518741}, {"model_based_pick": false}]
[[0, 0, 13], {"dropout1_rate": 0.7191081759928882, "dropout2_rate": 0.29994384328903606, "lr": 0.010280751032337424, "num_dense_layers": 3, "optimizer": "SGD", "start_neurons_units": 280, "dense1_units": 24, "dense2_units": 7, "sgd_momentum": 0.33993712421544336}, {"model_based_pick": false}]
[[0, 0, 14], {"dropout1_rate": 0.657239339310198, "dropout2_rate": 0.393185847977028, "lr": 0.024189723580008336, "num_dense_layers": 2, "optimizer": "Adam", "start_neurons_units": 77, "dense1_units": 37}, {"model_based_pick": false}]
[[0, 0, 15], {"dropout1_rate": 0.20441687660912813, "dropout2_rate": 0.25281719729807517, "lr": 4.118377278460709e-05, "num_dense_layers": 2, "optimizer": "Adam", "start_neurons_units": 109, "dense1_units": 26}, {"model_based_pick": false}]
[[0, 0, 16], {"dropout1_rate": 0.17247198265830382, "dropout2_rate": 0.6632151473119626, "lr": 0.007150484191538183, "num_dense_layers": 2, "optimizer": "Adam", "start_neurons_units": 65, "dense1_units": 10}, {"model_based_pick": false}]
[[0, 0, 17], {"dropout1_rate": 0.07592121238646819, "dropout2_rate": 0.3137265080318252, "lr": 0.025407882423184112, "num_dense_layers": 3, "optimizer": "SGD", "start_neurons_units": 461, "dense1_units": 29, "dense2_units": 9, "sgd_momentum": 0.10268687842556679}, {"model_based_pick": false}]
[[0, 0, 18], {"dropout1_rate": 0.5376811048430223, "dropout2_rate": 0.7770085147454308, "lr": 0.00011762831268849415, "num_dense_layers": 3, "optimizer": "Adam", "start_neurons_units": 145, "dense1_units": 11, "dense2_units": 10}, {"model_based_pick": false}]
[[0, 0, 19], {"dropout1_rate": 0.4449091966983748, "dropout2_rate": 0.15415091346897455, "lr": 5.3704796627483156e-05, "num_dense_layers": 1, "optimizer": "SGD", "start_neurons_units": 378, "sgd_momentum": 0.20953064304640487}, {"model_based_pick": false}]
[[0, 0, 20], {"dropout1_rate": 0.0795183301748757, "dropout2_rate": 0.1741324881697596, "lr": 0.0035530224417929432, "num_dense_layers": 1, "optimizer": "SGD", "start_neurons_units": 213, "sgd_momentum": 0.05445418023079075}, {"model_based_pick": false}]
[[0, 0, 21], {"dropout1_rate": 0.1627952560765778, "dropout2_rate": 0.680898055926448, "lr": 4.0181515013130775e-05, "num_dense_layers": 1, "optimizer": "SGD", "start_neurons_units": 33, "sgd_momentum": 0.057174718375760346}, {"model_based_pick": false}]
[[0, 0, 22], {"dropout1_rate": 0.1289008711979602, "dropout2_rate": 0.7203197973680664, "lr": 0.008873030438814608, "num_dense_layers": 1, "optimizer": "SGD", "start_neurons_units": 32, "sgd_momentum": 0.187226124855558}, {"model_based_pick": false}]
[[0, 0, 23], {"dropout1_rate": 0.859428473458394, "dropout2_rate": 0.2854427379932666, "lr": 0.0004714320513543389, "num_dense_layers": 1, "optimizer": "SGD", "start_neurons_units": 44, "sgd_momentum": 0.9062639747387337}, {"model_based_pick": false}]
[[0, 0, 24], {"dropout1_rate": 0.5676845698457968, "dropout2_rate": 0.8763346121156923, "lr": 1.6814015407087277e-05, "num_dense_layers": 2, "optimizer": "Adam", "start_neurons_units": 48, "dense1_units": 73}, {"model_based_pick": false}]
[[0, 0, 25], {"dropout1_rate": 0.09514162640989235, "dropout2_rate": 0.7486887811504648, "lr": 1.0289223494080111e-05, "num_dense_layers": 1, "optimizer": "Adam", "start_neurons_units": 203}, {"model_based_pick": false}]
[[0, 0, 26], {"dropout1_rate": 0.46318274191329084, "dropout2_rate": 0.8951003291683441, "lr": 2.141231989423273e-06, "num_dense_layers": 2, "optimizer": "SGD", "start_neurons_units": 218, "dense1_units": 10, "sgd_momentum": 0.34445416060139356}, {"model_based_pick": false}]
